spigetpy/__init__.py
spigetpy/authors.py
spigetpy/categories.py
spigetpy/resources.py
spigetpy/search.py
spigetpy/status.py
spigetpy/utils.py
spigetpy/webhook.py
spigetpy-0.0.1.dist-info/LICENSE.md
spigetpy-0.0.1.dist-info/METADATA
spigetpy-0.0.1.dist-info/WHEEL
spigetpy-0.0.1.dist-info/top_level.txt
spigetpy-0.0.1.dist-info/RECORD
